sagemaker_rightline/__init__.py
sagemaker_rightline/model.py
sagemaker_rightline/rules.py
sagemaker_rightline/validations.py
sagemaker_rightline-0.3.7.dist-info/LICENSE
sagemaker_rightline-0.3.7.dist-info/METADATA
sagemaker_rightline-0.3.7.dist-info/WHEEL
sagemaker_rightline-0.3.7.dist-info/top_level.txt
sagemaker_rightline-0.3.7.dist-info/RECORD
