Metadata-Version: 2.1
Name: sagemaker-rightline
Version: 0.3.7
Summary: Python package to easily validate properties of a SageMaker Pipeline.
Author-email: stiebels <stiebels@github.com>, dipanjank <dipanjank@github.com>
License: MIT License
Project-URL: Homepage, https://github.com/stiebels/sagemaker-rightline
Keywords: sagemaker,pipeline,validation
Classifier: Development Status :: 4 - Beta
Classifier: Intended Audience :: Developers
Classifier: Topic :: Software Development :: Libraries :: Python Modules
Classifier: Topic :: Software Development :: Testing
Classifier: License :: OSI Approved :: MIT License
Classifier: Programming Language :: Python :: 3
Classifier: Programming Language :: Python :: 3.8
Classifier: Programming Language :: Python :: 3.9
Classifier: Programming Language :: Python :: 3.10
Classifier: Programming Language :: Python :: 3.11
Classifier: Programming Language :: Python :: 3.12
Classifier: Programming Language :: Python :: 3 :: Only
Requires-Python: <3.13,>3.7
License-File: LICENSE
Requires-Dist: boto3 >=1.26
Requires-Dist: pandas >=2.0.3
Requires-Dist: sagemaker >=2.159
Provides-Extra: dev
Requires-Dist: moto[all] ; extra == 'dev'
Requires-Dist: pytest ; extra == 'dev'
Requires-Dist: pytest-cov ; extra == 'dev'
Requires-Dist: pyproject-flake8 ; extra == 'dev'
Requires-Dist: jupyter ; extra == 'dev'
Requires-Dist: build ; extra == 'dev'
